shpaste/__init__.py
shpaste/__main__.py
shpaste/__version__.py
shpaste-0.1.5.dist-info/METADATA
shpaste-0.1.5.dist-info/WHEEL
shpaste-0.1.5.dist-info/entry_points.txt
shpaste-0.1.5.dist-info/top_level.txt
shpaste-0.1.5.dist-info/RECORD
