Metadata-Version: 2.1
Name: shpaste
Version: 0.1.5
Summary: A cli tool for uploading pastes to paste.sh.ht
Home-page: https://github.com/me/myproject
Author: Joshua Mulliken
Author-email: joshua@mulliken.net
License: GPLv3
Platform: UNKNOWN
Classifier: License :: OSI Approved :: GNU General Public License v3 (GPLv3)
Classifier: Programming Language :: Python
Classifier: Programming Language :: Python :: 3
Classifier: Programming Language :: Python :: 3.6
Classifier: Programming Language :: Python :: Implementation :: CPython
Classifier: Programming Language :: Python :: Implementation :: PyPy
Requires-Python: >=3.6.0
Requires-Dist: appdirs
Requires-Dist: requests
